dinero/__init__.py
dinero/_base.py
dinero/_dinero.py
dinero/_operations.py
dinero/_utils.py
dinero/_validators.py
dinero/currencies/__init__.py
dinero/currencies/_aed.py
dinero/currencies/_afn.py
dinero/currencies/_amd.py
dinero/currencies/_aoa.py
dinero/currencies/_ars.py
dinero/currencies/_aud.py
dinero/currencies/_awg.py
dinero/currencies/_azn.py
dinero/currencies/_bbd.py
dinero/currencies/_bdt.py
dinero/currencies/_bgn.py
dinero/currencies/_bhd.py
dinero/currencies/_bif.py
dinero/currencies/_bmd.py
dinero/currencies/_bnd.py
dinero/currencies/_bov.py
dinero/currencies/_brl.py
dinero/currencies/_bwp.py
dinero/currencies/_byn.py
dinero/currencies/_bzd.py
dinero/currencies/_cdf.py
dinero/currencies/_che.py
dinero/currencies/_chf.py
dinero/currencies/_chw.py
dinero/currencies/_clp.py
dinero/currencies/_cny.py
dinero/currencies/_cop.py
dinero/currencies/_cou.py
dinero/currencies/_crc.py
dinero/currencies/_cuc.py
dinero/currencies/_cve.py
dinero/currencies/_czk.py
dinero/currencies/_djf.py
dinero/currencies/_dkk.py
dinero/currencies/_dop.py
dinero/currencies/_dzd.py
dinero/currencies/_egp.py
dinero/currencies/_etb.py
dinero/currencies/_eur.py
dinero/currencies/_fjd.py
dinero/currencies/_fkp.py
dinero/currencies/_gbp.py
dinero/currencies/_gtq.py
dinero/currencies/_hrk.py
dinero/currencies/_htg.py
dinero/currencies/_idr.py
dinero/currencies/_ils.py
dinero/currencies/_inr.py
dinero/currencies/_iqd.py
dinero/currencies/_irr.py
dinero/currencies/_isk.py
dinero/currencies/_jmd.py
dinero/currencies/_jpy.py
dinero/currencies/_kes.py
dinero/currencies/_kgs.py
dinero/currencies/_khr.py
dinero/currencies/_kmf.py
dinero/currencies/_krw.py
dinero/currencies/_kwd.py
dinero/currencies/_kzt.py
dinero/currencies/_lak.py
dinero/currencies/_lkr.py
dinero/currencies/_lrd.py
dinero/currencies/_lsl.py
dinero/currencies/_mad.py
dinero/currencies/_mdl.py
dinero/currencies/_mga.py
dinero/currencies/_mmk.py
dinero/currencies/_mnt.py
dinero/currencies/_mop.py
dinero/currencies/_mur.py
dinero-0.4.0.dist-info/LICENSE
dinero-0.4.0.dist-info/METADATA
dinero-0.4.0.dist-info/WHEEL
dinero-0.4.0.dist-info/RECORD
