Metadata-Version: 2.3
Name: dinero
Version: 0.4.0
Summary: Dinero is a library for working with monetary values in Python.
Home-page: https://github.com/wilfredinni/dinero
License: MIT
Keywords: python3,money,decimals,calculations,currency
Author: Carlos Montecinos Geisse
Author-email: carlos@pythoncheatsheet.org
Requires-Python: >=3.10,<4.0
Classifier: License :: OSI Approved :: MIT License
Classifier: Programming Language :: Python :: 3
Classifier: Programming Language :: Python :: 3.10
Classifier: Programming Language :: Python :: 3.11
Classifier: Programming Language :: Python :: 3.12
Classifier: Programming Language :: Python :: 3.13
Requires-Dist: typing-extensions (>=4.12.2,<5.0.0)
Project-URL: Repository, https://github.com/wilfredinni/dinero
